{
  "scannedAt": "2026-05-28T22:58:21.732Z",
  "scanDateET": "2026-05-28",
  "total": 5000,
  "count": 146,
  "alerts": [
    {
      "symbol": "CVNA",
      "close": 73.49,
      "ema9": 70.1961,
      "sma50": 70.2367,
      "sma200": 73.8034,
      "ratio": 0.9994,
      "daysOutside": 5
    },
    {
      "symbol": "CTVA",
      "close": 80.6,
      "ema9": 80.1455,
      "sma50": 81.2774,
      "sma200": 72.4966,
      "ratio": 0.9861,
      "daysOutside": 5
    },
    {
      "symbol": "IE",
      "close": 13.72,
      "ema9": 12.9376,
      "sma50": 12.96,
      "sma200": 13.7041,
      "ratio": 0.9983,
      "daysOutside": 5
    },
    {
      "symbol": "BRSP",
      "close": 5.75,
      "ema9": 5.7327,
      "sma50": 5.78,
      "sma200": 5.6925,
      "ratio": 0.9918,
      "daysOutside": 5
    },
    {
      "symbol": "BG",
      "close": 123.7,
      "ema9": 122.1673,
      "sma50": 124.427,
      "sma200": 104.1771,
      "ratio": 0.9818,
      "daysOutside": 6
    },
    {
      "symbol": "AGNC",
      "close": 10.55,
      "ema9": 10.4338,
      "sma50": 10.4788,
      "sma200": 10.515,
      "ratio": 0.9957,
      "daysOutside": 6
    },
    {
      "symbol": "AG",
      "close": 20.58,
      "ema9": 20.2824,
      "sma50": 20.6288,
      "sma200": 17.3675,
      "ratio": 0.9832,
      "daysOutside": 6
    },
    {
      "symbol": "SBSW",
      "close": 12.16,
      "ema9": 12.0595,
      "sma50": 12.4038,
      "sma200": 12.6925,
      "ratio": 0.9722,
      "daysOutside": 6
    },
    {
      "symbol": "TEX",
      "close": 59.17,
      "ema9": 59.0733,
      "sma50": 60.4954,
      "sma200": 56.2772,
      "ratio": 0.9765,
      "daysOutside": 6
    },
    {
      "symbol": "UEC",
      "close": 13.55,
      "ema9": 13.5142,
      "sma50": 14.0138,
      "sma200": 13.7924,
      "ratio": 0.9643,
      "daysOutside": 6
    },
    {
      "symbol": "FUL",
      "close": 63.59,
      "ema9": 60.2403,
      "sma50": 59.8138,
      "sma200": 60.2677,
      "ratio": 1.0071,
      "daysOutside": 6
    },
    {
      "symbol": "OLN",
      "close": 26.75,
      "ema9": 26.5145,
      "sma50": 27.5342,
      "sma200": 23.995,
      "ratio": 0.963,
      "daysOutside": 6
    },
    {
      "symbol": "DX",
      "close": 13.03,
      "ema9": 12.9925,
      "sma50": 13.1132,
      "sma200": 13.3433,
      "ratio": 0.9908,
      "daysOutside": 6
    },
    {
      "symbol": "ARR",
      "close": 17.11,
      "ema9": 16.9231,
      "sma50": 17.066,
      "sma200": 16.7837,
      "ratio": 0.9916,
      "daysOutside": 6
    },
    {
      "symbol": "BCAX",
      "close": 21.75,
      "ema9": 21.3747,
      "sma50": 21.3473,
      "sma200": 17.1637,
      "ratio": 1.0013,
      "daysOutside": 6
    },
    {
      "symbol": "EVLV",
      "close": 6.51,
      "ema9": 6.252,
      "sma50": 6.3055,
      "sma200": 6.7633,
      "ratio": 0.9915,
      "daysOutside": 6
    },
    {
      "symbol": "NVA",
      "close": 6.75,
      "ema9": 6.1391,
      "sma50": 6.027,
      "sma200": 6.4552,
      "ratio": 1.0186,
      "daysOutside": 6
    },
    {
      "symbol": "WPM",
      "close": 130.07,
      "ema9": 129.5605,
      "sma50": 133.325,
      "sma200": 121.7077,
      "ratio": 0.9718,
      "daysOutside": 7
    },
    {
      "symbol": "AU",
      "close": 96.31,
      "ema9": 95.0745,
      "sma50": 97.3076,
      "sma200": 86.8194,
      "ratio": 0.9771,
      "daysOutside": 7
    },
    {
      "symbol": "CCJ",
      "close": 110.63,
      "ema9": 108.4749,
      "sma50": 113.3676,
      "sma200": 100.5886,
      "ratio": 0.9568,
      "daysOutside": 7
    },
    {
      "symbol": "HL",
      "close": 17.59,
      "ema9": 17.5413,
      "sma50": 18.3986,
      "sma200": 17.1374,
      "ratio": 0.9534,
      "daysOutside": 7
    },
    {
      "symbol": "CRSP",
      "close": 56.38,
      "ema9": 52.0959,
      "sma50": 51.3013,
      "sma200": 55.7175,
      "ratio": 1.0155,
      "daysOutside": 7
    },
    {
      "symbol": "FSM",
      "close": 9.81,
      "ema9": 9.6738,
      "sma50": 9.9208,
      "sma200": 9.5722,
      "ratio": 0.9751,
      "daysOutside": 7
    },
    {
      "symbol": "IMNM",
      "close": 22.54,
      "ema9": 21.9578,
      "sma50": 22.1108,
      "sma200": 18.6584,
      "ratio": 0.9931,
      "daysOutside": 7
    },
    {
      "symbol": "CLDX",
      "close": 31.7,
      "ema9": 31.3336,
      "sma50": 32.1694,
      "sma200": 27.4464,
      "ratio": 0.974,
      "daysOutside": 7
    },
    {
      "symbol": "NTLA",
      "close": 13.68,
      "ema9": 13.0781,
      "sma50": 13.5575,
      "sma200": 13.26,
      "ratio": 0.9646,
      "daysOutside": 7
    },
    {
      "symbol": "GILT",
      "close": 17.83,
      "ema9": 16.9008,
      "sma50": 17.3958,
      "sma200": 14.5302,
      "ratio": 0.9715,
      "daysOutside": 7
    },
    {
      "symbol": "DSL",
      "close": 11.04,
      "ema9": 10.9356,
      "sma50": 10.9342,
      "sma200": 11.4986,
      "ratio": 1.0001,
      "daysOutside": 7
    },
    {
      "symbol": "PRTA",
      "close": 9.98,
      "ema9": 9.8458,
      "sma50": 10.085,
      "sma200": 9.6044,
      "ratio": 0.9763,
      "daysOutside": 7
    },
    {
      "symbol": "NTRA",
      "close": 213.94,
      "ema9": 203.6246,
      "sma50": 202.0036,
      "sma200": 202.3841,
      "ratio": 1.008,
      "daysOutside": 8
    },
    {
      "symbol": "SW",
      "close": 41.02,
      "ema9": 39.148,
      "sma50": 39.8668,
      "sma200": 41.1761,
      "ratio": 0.982,
      "daysOutside": 8
    },
    {
      "symbol": "SSB",
      "close": 94.69,
      "ema9": 94.4637,
      "sma50": 94.9592,
      "sma200": 96.2814,
      "ratio": 0.9948,
      "daysOutside": 8
    },
    {
      "symbol": "VFC",
      "close": 17.93,
      "ema9": 17.1806,
      "sma50": 18.0222,
      "sma200": 17.1172,
      "ratio": 0.9533,
      "daysOutside": 8
    },
    {
      "symbol": "WH",
      "close": 82.61,
      "ema9": 81.2709,
      "sma50": 82.4208,
      "sma200": 79.6826,
      "ratio": 0.986,
      "daysOutside": 8
    },
    {
      "symbol": "XENE",
      "close": 54.79,
      "ema9": 54.4988,
      "sma50": 56.0774,
      "sma200": 45.3653,
      "ratio": 0.9718,
      "daysOutside": 8
    },
    {
      "symbol": "AMRX",
      "close": 12.95,
      "ema9": 12.5956,
      "sma50": 12.6279,
      "sma200": 11.9923,
      "ratio": 0.9974,
      "daysOutside": 8
    },
    {
      "symbol": "DAN",
      "close": 36.17,
      "ema9": 34.8518,
      "sma50": 34.8678,
      "sma200": 26.8907,
      "ratio": 0.9995,
      "daysOutside": 8
    },
    {
      "symbol": "AMPX",
      "close": 20.85,
      "ema9": 17.6091,
      "sma50": 18.2502,
      "sma200": 12.8134,
      "ratio": 0.9649,
      "daysOutside": 8
    },
    {
      "symbol": "SPRY",
      "close": 9.4,
      "ema9": 8.3457,
      "sma50": 8.1968,
      "sma200": 9.7285,
      "ratio": 1.0182,
      "daysOutside": 8
    },
    {
      "symbol": "XNCR",
      "close": 11.97,
      "ema9": 11.6387,
      "sma50": 12.2036,
      "sma200": 12.5641,
      "ratio": 0.9537,
      "daysOutside": 8
    },
    {
      "symbol": "DHI",
      "close": 146.92,
      "ema9": 144.2779,
      "sma50": 144.5308,
      "sma200": 153.8367,
      "ratio": 0.9983,
      "daysOutside": 9
    },
    {
      "symbol": "CRL",
      "close": 181.34,
      "ema9": 164.334,
      "sma50": 168.5922,
      "sma200": 176.1474,
      "ratio": 0.9747,
      "daysOutside": 9
    },
    {
      "symbol": "EBC",
      "close": 19.82,
      "ema9": 19.8138,
      "sma50": 19.8972,
      "sma200": 18.9601,
      "ratio": 0.9958,
      "daysOutside": 9
    },
    {
      "symbol": "VLRS",
      "close": 7.72,
      "ema9": 7.188,
      "sma50": 7.3238,
      "sma200": 7.5654,
      "ratio": 0.9815,
      "daysOutside": 9
    },
    {
      "symbol": "HBAN",
      "close": 16.12,
      "ema9": 15.929,
      "sma50": 16.045,
      "sma200": 16.7476,
      "ratio": 0.9928,
      "daysOutside": 10
    },
    {
      "symbol": "FLR",
      "close": 46.97,
      "ema9": 45.9479,
      "sma50": 47.631,
      "sma200": 45.2903,
      "ratio": 0.9647,
      "daysOutside": 10
    },
    {
      "symbol": "BYD",
      "close": 83.21,
      "ema9": 81.1325,
      "sma50": 83.7172,
      "sma200": 83.6454,
      "ratio": 0.9691,
      "daysOutside": 10
    },
    {
      "symbol": "KTB",
      "close": 73.75,
      "ema9": 70.0948,
      "sma50": 70.6736,
      "sma200": 71.5539,
      "ratio": 0.9918,
      "daysOutside": 10
    },
    {
      "symbol": "AVNT",
      "close": 36.18,
      "ema9": 35.1269,
      "sma50": 35.8868,
      "sma200": 34.7356,
      "ratio": 0.9788,
      "daysOutside": 10
    },
    {
      "symbol": "VIR",
      "close": 9.55,
      "ema9": 9.214,
      "sma50": 9.5353,
      "sma200": 7.1411,
      "ratio": 0.9663,
      "daysOutside": 10
    },
    {
      "symbol": "MAN",
      "close": 30.33,
      "ema9": 28.859,
      "sma50": 28.976,
      "sma200": 31.9056,
      "ratio": 0.996,
      "daysOutside": 10
    },
    {
      "symbol": "WMS",
      "close": 140.05,
      "ema9": 138.0434,
      "sma50": 142.4696,
      "sma200": 147.3025,
      "ratio": 0.9689,
      "daysOutside": 11
    },
    {
      "symbol": "BOOT",
      "close": 170.77,
      "ema9": 158.3867,
      "sma50": 157.1006,
      "sma200": 177.1862,
      "ratio": 1.0082,
      "daysOutside": 11
    },
    {
      "symbol": "ZYME",
      "close": 25.48,
      "ema9": 25.0976,
      "sma50": 25.8229,
      "sma200": 22.1144,
      "ratio": 0.9719,
      "daysOutside": 11
    },
    {
      "symbol": "ZD",
      "close": 45.07,
      "ema9": 43.6917,
      "sma50": 44.0026,
      "sma200": 37.7781,
      "ratio": 0.9929,
      "daysOutside": 11
    },
    {
      "symbol": "APH",
      "close": 147.68,
      "ema9": 134.8533,
      "sma50": 135.4314,
      "sma200": 133.4287,
      "ratio": 0.9957,
      "daysOutside": 12
    },
    {
      "symbol": "A",
      "close": 135.38,
      "ema9": 118.5441,
      "sma50": 115.3788,
      "sma200": 129.5218,
      "ratio": 1.0274,
      "daysOutside": 12
    },
    {
      "symbol": "FIVE",
      "close": 224.9,
      "ema9": 219.5754,
      "sma50": 225.9586,
      "sma200": 186.6863,
      "ratio": 0.9718,
      "daysOutside": 12
    },
    {
      "symbol": "SFD",
      "close": 26.4,
      "ema9": 26.2048,
      "sma50": 26.8481,
      "sma200": 24.1401,
      "ratio": 0.976,
      "daysOutside": 12
    },
    {
      "symbol": "LEG",
      "close": 10.38,
      "ema9": 10.0541,
      "sma50": 10.341,
      "sma200": 10.3751,
      "ratio": 0.9723,
      "daysOutside": 12
    },
    {
      "symbol": "UPBD",
      "close": 19.42,
      "ema9": 18.2776,
      "sma50": 18.443,
      "sma200": 20.2218,
      "ratio": 0.991,
      "daysOutside": 12
    },
    {
      "symbol": "EAT",
      "close": 140.02,
      "ema9": 137.699,
      "sma50": 143.5868,
      "sma200": 143.3653,
      "ratio": 0.959,
      "daysOutside": 13
    },
    {
      "symbol": "BXMT",
      "close": 18.28,
      "ema9": 18.2715,
      "sma50": 19.0232,
      "sma200": 19.1308,
      "ratio": 0.9605,
      "daysOutside": 13
    },
    {
      "symbol": "ADPT",
      "close": 15.19,
      "ema9": 14.0116,
      "sma50": 13.8826,
      "sma200": 15.1569,
      "ratio": 1.0093,
      "daysOutside": 13
    },
    {
      "symbol": "META",
      "close": 635.29,
      "ema9": 619.4999,
      "sma50": 618.1954,
      "sma200": 667.3589,
      "ratio": 1.0021,
      "daysOutside": 14
    },
    {
      "symbol": "EA",
      "close": 201.15,
      "ema9": 201.1072,
      "sma50": 202.0386,
      "sma200": 197.0381,
      "ratio": 0.9954,
      "daysOutside": 14
    },
    {
      "symbol": "CWEN",
      "close": 40.63,
      "ema9": 39.0693,
      "sma50": 39.0734,
      "sma200": 34.936,
      "ratio": 0.9999,
      "daysOutside": 14
    },
    {
      "symbol": "DYN",
      "close": 18.56,
      "ema9": 17.8431,
      "sma50": 18.2498,
      "sma200": 17.2581,
      "ratio": 0.9777,
      "daysOutside": 14
    },
    {
      "symbol": "LILAK",
      "close": 8.13,
      "ema9": 7.9879,
      "sma50": 8.247,
      "sma200": 8.0842,
      "ratio": 0.9686,
      "daysOutside": 14
    },
    {
      "symbol": "MFA",
      "close": 9.6,
      "ema9": 9.5505,
      "sma50": 9.8158,
      "sma200": 9.6888,
      "ratio": 0.973,
      "daysOutside": 14
    },
    {
      "symbol": "UPS",
      "close": 106.67,
      "ema9": 101.7972,
      "sma50": 100.9182,
      "sma200": 98.0121,
      "ratio": 1.0087,
      "daysOutside": 15
    },
    {
      "symbol": "COGT",
      "close": 35.38,
      "ema9": 33.8491,
      "sma50": 35.3766,
      "sma200": 29.5154,
      "ratio": 0.9568,
      "daysOutside": 15
    },
    {
      "symbol": "CNK",
      "close": 27.24,
      "ema9": 26.9043,
      "sma50": 28.1416,
      "sma200": 26.5953,
      "ratio": 0.956,
      "daysOutside": 15
    },
    {
      "symbol": "BCRX",
      "close": 9.1,
      "ema9": 8.8324,
      "sma50": 9.1836,
      "sma200": 7.9212,
      "ratio": 0.9618,
      "daysOutside": 15
    },
    {
      "symbol": "WY",
      "close": 24.56,
      "ema9": 23.8414,
      "sma50": 24.0246,
      "sma200": 24.3434,
      "ratio": 0.9924,
      "daysOutside": 16
    },
    {
      "symbol": "BBIO",
      "close": 68.45,
      "ema9": 67.8864,
      "sma50": 71.0514,
      "sma200": 66.285,
      "ratio": 0.9555,
      "daysOutside": 16
    },
    {
      "symbol": "ONDS",
      "close": 13.25,
      "ema9": 10.464,
      "sma50": 9.8803,
      "sma200": 8.8549,
      "ratio": 1.0591,
      "daysOutside": 16
    },
    {
      "symbol": "PCAR",
      "close": 112.22,
      "ema9": 111.6695,
      "sma50": 117.4786,
      "sma200": 110.7272,
      "ratio": 0.9506,
      "daysOutside": 17
    },
    {
      "symbol": "HCC",
      "close": 104.58,
      "ema9": 92.03,
      "sma50": 89.3684,
      "sma200": 79.8023,
      "ratio": 1.0298,
      "daysOutside": 17
    },
    {
      "symbol": "BBT",
      "close": 29.07,
      "ema9": 28.8443,
      "sma50": 29.9116,
      "sma200": 27.4993,
      "ratio": 0.9643,
      "daysOutside": 17
    },
    {
      "symbol": "GNL",
      "close": 9.49,
      "ema9": 9.3988,
      "sma50": 9.383,
      "sma200": 8.705,
      "ratio": 1.0017,
      "daysOutside": 17
    },
    {
      "symbol": "FHI",
      "close": 55.47,
      "ema9": 55.293,
      "sma50": 56.1324,
      "sma200": 53.4242,
      "ratio": 0.985,
      "daysOutside": 18
    },
    {
      "symbol": "SOC",
      "close": 14.69,
      "ema9": 14.2517,
      "sma50": 14.5724,
      "sma200": 13.6771,
      "ratio": 0.978,
      "daysOutside": 18
    },
    {
      "symbol": "TEL",
      "close": 210.33,
      "ema9": 206.3922,
      "sma50": 212.5786,
      "sma200": 221.0507,
      "ratio": 0.9709,
      "daysOutside": 19
    },
    {
      "symbol": "KGC",
      "close": 29.29,
      "ema9": 29.0696,
      "sma50": 30.586,
      "sma200": 28.3277,
      "ratio": 0.9504,
      "daysOutside": 20
    },
    {
      "symbol": "RPM",
      "close": 106.91,
      "ema9": 101.9526,
      "sma50": 101.5738,
      "sma200": 109.7522,
      "ratio": 1.0037,
      "daysOutside": 20
    },
    {
      "symbol": "TOL",
      "close": 138.14,
      "ema9": 135.6834,
      "sma50": 137.8828,
      "sma200": 140.1558,
      "ratio": 0.984,
      "daysOutside": 20
    },
    {
      "symbol": "HSIC",
      "close": 76.32,
      "ema9": 74.158,
      "sma50": 74.3014,
      "sma200": 72.9023,
      "ratio": 0.9981,
      "daysOutside": 20
    },
    {
      "symbol": "SMG",
      "close": 60.48,
      "ema9": 59.5346,
      "sma50": 62.1196,
      "sma200": 60.6255,
      "ratio": 0.9584,
      "daysOutside": 20
    },
    {
      "symbol": "WSBC",
      "close": 34.69,
      "ema9": 34.3493,
      "sma50": 34.433,
      "sma200": 33.5027,
      "ratio": 0.9976,
      "daysOutside": 20
    },
    {
      "symbol": "GAP",
      "close": 25,
      "ema9": 23.2923,
      "sma50": 24.265,
      "sma200": 24.5605,
      "ratio": 0.9599,
      "daysOutside": 21
    },
    {
      "symbol": "GGAL",
      "close": 48.83,
      "ema9": 45.0879,
      "sma50": 44.557,
      "sma200": 45.2512,
      "ratio": 1.0119,
      "daysOutside": 21
    },
    {
      "symbol": "VKTX",
      "close": 32.19,
      "ema9": 31.0137,
      "sma50": 32.5331,
      "sma200": 32.521,
      "ratio": 0.9533,
      "daysOutside": 21
    },
    {
      "symbol": "ASO",
      "close": 55.12,
      "ema9": 52.715,
      "sma50": 54.4254,
      "sma200": 53.0206,
      "ratio": 0.9686,
      "daysOutside": 21
    },
    {
      "symbol": "SUPV",
      "close": 9.29,
      "ema9": 8.4724,
      "sma50": 8.7572,
      "sma200": 9.2988,
      "ratio": 0.9675,
      "daysOutside": 21
    },
    {
      "symbol": "TPR",
      "close": 145.39,
      "ema9": 138.6559,
      "sma50": 142.2638,
      "sma200": 126.8296,
      "ratio": 0.9746,
      "daysOutside": 22
    },
    {
      "symbol": "SIG",
      "close": 86.99,
      "ema9": 82.2453,
      "sma50": 86.2904,
      "sma200": 91.1742,
      "ratio": 0.9531,
      "daysOutside": 22
    },
    {
      "symbol": "GSK",
      "close": 51.24,
      "ema9": 51.2113,
      "sma50": 53.6194,
      "sma200": 49.2041,
      "ratio": 0.9551,
      "daysOutside": 23
    },
    {
      "symbol": "LBTYA",
      "close": 12.21,
      "ema9": 12.077,
      "sma50": 12.0804,
      "sma200": 11.5469,
      "ratio": 0.9997,
      "daysOutside": 23
    },
    {
      "symbol": "PFE",
      "close": 26.14,
      "ema9": 25.9542,
      "sma50": 26.757,
      "sma200": 25.8268,
      "ratio": 0.97,
      "daysOutside": 24
    },
    {
      "symbol": "BBY",
      "close": 74.74,
      "ema9": 63.8555,
      "sma50": 61.8064,
      "sma200": 69.7394,
      "ratio": 1.0332,
      "daysOutside": 24
    },
    {
      "symbol": "TNL",
      "close": 68.3,
      "ema9": 66.0915,
      "sma50": 68.6592,
      "sma200": 67.3852,
      "ratio": 0.9626,
      "daysOutside": 24
    },
    {
      "symbol": "LBTYK",
      "close": 11.87,
      "ema9": 11.744,
      "sma50": 11.7404,
      "sma200": 11.4669,
      "ratio": 1.0003,
      "daysOutside": 24
    },
    {
      "symbol": "DNLI",
      "close": 20.95,
      "ema9": 19.5954,
      "sma50": 19.6687,
      "sma200": 17.9231,
      "ratio": 0.9963,
      "daysOutside": 24
    },
    {
      "symbol": "BEPC",
      "close": 39.86,
      "ema9": 38.199,
      "sma50": 39.2384,
      "sma200": 39.0604,
      "ratio": 0.9735,
      "daysOutside": 25
    },
    {
      "symbol": "IDYA",
      "close": 29.34,
      "ema9": 29.125,
      "sma50": 30.4946,
      "sma200": 30.8621,
      "ratio": 0.9551,
      "daysOutside": 25
    },
    {
      "symbol": "FE",
      "close": 46.19,
      "ema9": 45.9062,
      "sma50": 48.2672,
      "sma200": 46.7156,
      "ratio": 0.9511,
      "daysOutside": 26
    },
    {
      "symbol": "POR",
      "close": 50.67,
      "ema9": 49.8639,
      "sma50": 50.9894,
      "sma200": 48.4087,
      "ratio": 0.9779,
      "daysOutside": 27
    },
    {
      "symbol": "EXC",
      "close": 45.58,
      "ema9": 45.4515,
      "sma50": 46.7778,
      "sma200": 45.7722,
      "ratio": 0.9716,
      "daysOutside": 28
    },
    {
      "symbol": "FAST",
      "close": 44.76,
      "ema9": 44.2334,
      "sma50": 44.9676,
      "sma200": 44.6675,
      "ratio": 0.9837,
      "daysOutside": 29
    },
    {
      "symbol": "KMX",
      "close": 43.9,
      "ema9": 40.3678,
      "sma50": 40.4674,
      "sma200": 44.307,
      "ratio": 0.9975,
      "daysOutside": 29
    },
    {
      "symbol": "IPGP",
      "close": 117.35,
      "ema9": 115.6314,
      "sma50": 116.1926,
      "sma200": 96.5057,
      "ratio": 0.9952,
      "daysOutside": 30
    },
    {
      "symbol": "JNJ",
      "close": 230.8,
      "ema9": 230.3193,
      "sma50": 232.7514,
      "sma200": 211.6125,
      "ratio": 0.9896,
      "daysOutside": 33
    },
    {
      "symbol": "VZ",
      "close": 48.01,
      "ema9": 47.935,
      "sma50": 47.9132,
      "sma200": 44.2641,
      "ratio": 1.0005,
      "daysOutside": 33
    },
    {
      "symbol": "DGX",
      "close": 196.2,
      "ema9": 193.2732,
      "sma50": 194.2874,
      "sma200": 188.2098,
      "ratio": 0.9948,
      "daysOutside": 42
    },
    {
      "symbol": "HSY",
      "close": 197.04,
      "ema9": 193.4571,
      "sma50": 197.095,
      "sma200": 193.7981,
      "ratio": 0.9815,
      "daysOutside": 43
    },
    {
      "symbol": "SUI",
      "close": 125,
      "ema9": 124.732,
      "sma50": 127.0748,
      "sma200": 127.1758,
      "ratio": 0.9816,
      "daysOutside": 43
    },
    {
      "symbol": "LAND",
      "close": 9.59,
      "ema9": 9.5431,
      "sma50": 10.0114,
      "sma200": 9.7709,
      "ratio": 0.9532,
      "daysOutside": 44
    },
    {
      "symbol": "RTX",
      "close": 178.96,
      "ema9": 176.9995,
      "sma50": 186.0048,
      "sma200": 180.6233,
      "ratio": 0.9516,
      "daysOutside": 45
    },
    {
      "symbol": "ALOY",
      "close": 9.73,
      "ema9": 9.5598,
      "sma50": 9.9982,
      "sma200": 9.5988,
      "ratio": 0.9562,
      "daysOutside": 45
    },
    {
      "symbol": "AMGN",
      "close": 336.48,
      "ema9": 334.969,
      "sma50": 342.1616,
      "sma200": 327.9712,
      "ratio": 0.979,
      "daysOutside": 46
    },
    {
      "symbol": "GILD",
      "close": 136.22,
      "ema9": 133.2529,
      "sma50": 135.2394,
      "sma200": 128.5834,
      "ratio": 0.9853,
      "daysOutside": 46
    },
    {
      "symbol": "PEG",
      "close": 79.15,
      "ema9": 78.8948,
      "sma50": 80.1368,
      "sma200": 81.5789,
      "ratio": 0.9845,
      "daysOutside": 46
    },
    {
      "symbol": "OMC",
      "close": 74.09,
      "ema9": 74.0393,
      "sma50": 75.6112,
      "sma200": 76.7703,
      "ratio": 0.9792,
      "daysOutside": 46
    },
    {
      "symbol": "SYY",
      "close": 75.92,
      "ema9": 75.2049,
      "sma50": 75.2914,
      "sma200": 78.5694,
      "ratio": 0.9989,
      "daysOutside": 47
    },
    {
      "symbol": "CAH",
      "close": 199.85,
      "ema9": 198.5481,
      "sma50": 203.3944,
      "sma200": 192.6076,
      "ratio": 0.9762,
      "daysOutside": 48
    },
    {
      "symbol": "PG",
      "close": 145.91,
      "ema9": 144.4505,
      "sma50": 144.5064,
      "sma200": 149.7305,
      "ratio": 0.9996,
      "daysOutside": 49
    },
    {
      "symbol": "VRTX",
      "close": 447.97,
      "ema9": 438.3481,
      "sma50": 438.751,
      "sma200": 435.768,
      "ratio": 0.9991,
      "daysOutside": 49
    },
    {
      "symbol": "IAG",
      "close": 17.36,
      "ema9": 17.0829,
      "sma50": 17.872,
      "sma200": 15.9163,
      "ratio": 0.9558,
      "daysOutside": 49
    },
    {
      "symbol": "BDX",
      "close": 148.41,
      "ema9": 147.0432,
      "sma50": 151.7304,
      "sma200": 154.5612,
      "ratio": 0.9691,
      "daysOutside": 52
    },
    {
      "symbol": "LH",
      "close": 262.75,
      "ema9": 258.1847,
      "sma50": 262.7476,
      "sma200": 268.4099,
      "ratio": 0.9826,
      "daysOutside": 52
    },
    {
      "symbol": "CDE",
      "close": 18.59,
      "ema9": 18.12,
      "sma50": 18.5762,
      "sma200": 18.5042,
      "ratio": 0.9754,
      "daysOutside": 52
    },
    {
      "symbol": "NEOG",
      "close": 9.3,
      "ema9": 8.977,
      "sma50": 9.1576,
      "sma200": 7.8367,
      "ratio": 0.9803,
      "daysOutside": 52
    },
    {
      "symbol": "EYPT",
      "close": 13.5,
      "ema9": 13.0456,
      "sma50": 13.4446,
      "sma200": 14.0157,
      "ratio": 0.9703,
      "daysOutside": 52
    },
    {
      "symbol": "ECL",
      "close": 260.25,
      "ema9": 255.0673,
      "sma50": 261.9772,
      "sma200": 271.6898,
      "ratio": 0.9736,
      "daysOutside": 53
    },
    {
      "symbol": "TKO",
      "close": 200.54,
      "ema9": 191.9709,
      "sma50": 191.0858,
      "sma200": 196.4873,
      "ratio": 1.0046,
      "daysOutside": 53
    },
    {
      "symbol": "CNH",
      "close": 10.46,
      "ema9": 10.4034,
      "sma50": 10.6366,
      "sma200": 10.7717,
      "ratio": 0.9781,
      "daysOutside": 53
    },
    {
      "symbol": "ELAN",
      "close": 23.98,
      "ema9": 22.3927,
      "sma50": 22.9718,
      "sma200": 22.1606,
      "ratio": 0.9748,
      "daysOutside": 54
    },
    {
      "symbol": "HRL",
      "close": 23.59,
      "ema9": 21.3307,
      "sma50": 21.3704,
      "sma200": 23.5647,
      "ratio": 0.9981,
      "daysOutside": 55
    },
    {
      "symbol": "MTN",
      "close": 134.02,
      "ema9": 128.0711,
      "sma50": 127.5072,
      "sma200": 140.8142,
      "ratio": 1.0044,
      "daysOutside": 56
    },
    {
      "symbol": "RCL",
      "close": 281.29,
      "ema9": 266.8095,
      "sma50": 269.0762,
      "sma200": 293.7367,
      "ratio": 0.9916,
      "daysOutside": 58
    },
    {
      "symbol": "DLTR",
      "close": 113,
      "ema9": 97.5501,
      "sma50": 100.2612,
      "sma200": 109.4348,
      "ratio": 0.973,
      "daysOutside": 61
    },
    {
      "symbol": "HOMB",
      "close": 26.88,
      "ema9": 26.5779,
      "sma50": 26.7988,
      "sma200": 27.9445,
      "ratio": 0.9918,
      "daysOutside": 62
    },
    {
      "symbol": "RRR",
      "close": 57.78,
      "ema9": 55.2539,
      "sma50": 55.0916,
      "sma200": 58.9634,
      "ratio": 1.0029,
      "daysOutside": 63
    },
    {
      "symbol": "ORC",
      "close": 6.95,
      "ema9": 6.8729,
      "sma50": 6.9946,
      "sma200": 7.2701,
      "ratio": 0.9826,
      "daysOutside": 70
    },
    {
      "symbol": "RYAAY",
      "close": 61.24,
      "ema9": 58.7943,
      "sma50": 58.2826,
      "sma200": 63.263,
      "ratio": 1.0088,
      "daysOutside": 76
    }
  ]
}
